CHANGES.txt
README.txt
TODO.txt
psycopgda-configure.zcml
setup.py
version.txt
psycopgda/__init__.py
psycopgda/adapter.py
psycopgda/configure.zcml
psycopgda/tests.py
psycopgda.egg-info/PKG-INFO
psycopgda.egg-info/SOURCES.txt
psycopgda.egg-info/dependency_links.txt
psycopgda.egg-info/top_level.txt
