Metadata-Version: 1.0
Name: psycopgda
Version: 1.0
Summary: Psycopg Database Adapter for Zope 3
Home-page: UNKNOWN
Author: Zope Corporation and Contributors
Author-email: zope3-dev@zope.org
License: ZPL 2.1
Platform: any
